{
  "Name":{
    "0":"villajo01",
    "1":"davisjd01",
    "2":"guilllu01",
    "3":"drurybr01",
    "4":"perazjo01",
    "5":"mcneije01",
    "6":"nidoto01"
  },
  "Age":{
    "0":30,
    "1":28,
    "2":26,
    "3":28,
    "4":27,
    "5":29,
    "6":27
  },
  "G":{
    "0":69,
    "1":45,
    "2":26,
    "3":7,
    "4":8,
    "5":2,
    "6":1
  },
  "GS":{
    "0":61,
    "1":43,
    "2":17,
    "3":5,
    "4":4,
    "5":0,
    "6":0
  },
  "CG":{
    "0":54,
    "1":32,
    "2":11,
    "3":3,
    "4":2,
    "5":0,
    "6":0
  },
  "Inn":{
    "0":"514.1",
    "1":"349.2",
    "2":"154.0",
    "3":"40.0",
    "4":"38.1",
    "5":"5.0",
    "6":"2.0"
  },
  "Ch":{
    "0":139,
    "1":91,
    "2":41,
    "3":16,
    "4":10,
    "5":2,
    "6":0
  },
  "PO":{
    "0":42,
    "1":33,
    "2":9,
    "3":4,
    "4":2,
    "5":0,
    "6":0
  },
  "A":{
    "0":90,
    "1":54,
    "2":29,
    "3":11,
    "4":7,
    "5":2,
    "6":0
  },
  "E":{
    "0":7,
    "1":4,
    "2":3,
    "3":1,
    "4":1,
    "5":0,
    "6":0
  },
  "DP":{
    "0":10,
    "1":5,
    "2":2,
    "3":2,
    "4":1,
    "5":0,
    "6":0
  },
  "Fld%":{
    "0":".950",
    "1":".956",
    "2":".927",
    "3":".938",
    "4":".900",
    "5":"1.000",
    "6":""
  }
}