{
  "Name":{
    "0":"kineris01",
    "1":"culbech01",
    "2":"hernayo02"
  },
  "Age":{
    "0":26,
    "1":32,
    "2":23
  },
  "G":{
    "0":128,
    "1":3,
    "2":2
  },
  "GS":{
    "0":127,
    "1":3,
    "2":0
  },
  "CG":{
    "0":125,
    "1":2,
    "2":0
  },
  "Inn":{
    "0":"1115.0",
    "1":"25.1",
    "2":"4.0"
  },
  "Ch":{
    "0":547,
    "1":10,
    "2":1
  },
  "PO":{
    "0":173,
    "1":2,
    "2":0
  },
  "A":{
    "0":361,
    "1":6,
    "2":1
  },
  "E":{
    "0":13,
    "1":2,
    "2":0
  },
  "DP":{
    "0":79,
    "1":1,
    "2":0
  },
  "Fld%":{
    "0":".976",
    "1":".800",
    "2":"1.000"
  }
}